setup.py
django_behave/__init__.py
django_behave/models.py
django_behave/runner.py
django_behave/splinter.steps_library.py
django_behave/tests.py
django_behave.egg-info/PKG-INFO
django_behave.egg-info/SOURCES.txt
django_behave.egg-info/dependency_links.txt
django_behave.egg-info/requires.txt
django_behave.egg-info/top_level.txt